dynacrop/__init__.py
dynacrop/api_handles.py
dynacrop/config.py
dynacrop/constants.py
dynacrop/exceptions.py
dynacrop/processing_request_base.py
dynacrop/sdk.py
dynacrop_sdk-0.0.1.post1.dist-info/METADATA
dynacrop_sdk-0.0.1.post1.dist-info/WHEEL
dynacrop_sdk-0.0.1.post1.dist-info/top_level.txt
dynacrop_sdk-0.0.1.post1.dist-info/RECORD
